LICENSE
MANIFEST.in
NOTICE
README.md
setup.cfg
setup.py
versioneer.py
bin/pxgrid_pyshark
bin/pxgrid_pyshark_file
pxgrid_pyshark_test/__init__.py
pxgrid_pyshark_test/_version.py
pxgrid_pyshark_test/endpointsdb.py
pxgrid_pyshark_test/ouidb.py
pxgrid_pyshark_test/parser.py
pxgrid_pyshark_test.egg-info/PKG-INFO
pxgrid_pyshark_test.egg-info/SOURCES.txt
pxgrid_pyshark_test.egg-info/dependency_links.txt
pxgrid_pyshark_test.egg-info/requires.txt
pxgrid_pyshark_test.egg-info/top_level.txt
pxgrid_pyshark_test/db/apple-os.json
pxgrid_pyshark_test/db/models.json